ninja_crud/__init__.py
ninja_crud/views/__init__.py
ninja_crud/views/api_view.py
ninja_crud/views/create_view.py
ninja_crud/views/delete_view.py
ninja_crud/views/list_view.py
ninja_crud/views/read_view.py
ninja_crud/views/update_view.py
ninja_crud/viewsets/__init__.py
ninja_crud/viewsets/api_viewset.py
django_ninja_crud-0.6.2.dist-info/LICENSE
django_ninja_crud-0.6.2.dist-info/METADATA
django_ninja_crud-0.6.2.dist-info/WHEEL
django_ninja_crud-0.6.2.dist-info/RECORD
